{
    "boxOfficeResult": {
        "boxofficeType": "일별 박스오피스",
        "showRange": "20240228~20240228",
        "dailyBoxOfficeList": [
            {
                "rnum": "1",
                "rank": "1",
                "rankInten": "0",
                "rankOldAndNew": "OLD",
                "movieCd": "20234675",
                "movieNm": "파묘",
                "openDt": "2024-02-22",
                "salesAmt": "3082112642",
                "salesShare": "59.0",
                "salesInten": "245469266",
                "salesChange": "8.7",
                "salesAcc": "31463851045",
                "audiCnt": "384594",
                "audiInten": "86130",
                "audiChange": "28.9",
                "audiAcc": "3312940",
                "scrnCnt": "1885",
                "showCnt": "7156"
            },
            {
                "rnum": "2",
                "rank": "2",
                "rankInten": "3",
                "rankOldAndNew": "OLD",
                "movieCd": "20236295",
                "movieNm": "듄: 파트2",
                "openDt": "2024-02-28",
                "salesAmt": "1447142430",
                "salesShare": "27.7",
                "salesInten": "1327022800",
                "salesChange": "1104.8",
                "salesAcc": "1596812060",
                "audiCnt": "152952",
                "audiInten": "146125",
                "audiChange": "2140.4",
                "audiAcc": "161609",
                "scrnCnt": "1544",
                "showCnt": "5047"
            },
            {
                "rnum": "3",
                "rank": "3",
                "rankInten": "-1",
                "rankOldAndNew": "OLD",
                "movieCd": "20236180",
                "movieNm": "웡카",
                "openDt": "2024-01-31",
                "salesAmt": "295801963",
                "salesShare": "5.7",
                "salesInten": "-87241445",
                "salesChange": "-22.8",
                "salesAcc": "29738475736",
                "audiCnt": "36777",
                "audiInten": "-5305",
                "audiChange": "-12.6",
                "audiAcc": "3088266",
                "scrnCnt": "645",
                "showCnt": "1243"
            },
            {
                "rnum": "4",
                "rank": "4",
                "rankInten": "-1",
                "rankOldAndNew": "OLD",
                "movieCd": "20247074",
                "movieNm": "건국전쟁",
                "openDt": "2024-02-01",
                "salesAmt": "113366451",
                "salesShare": "2.2",
                "salesInten": "-57097904",
                "salesChange": "-33.5",
                "salesAcc": "9514497308",
                "audiCnt": "13902",
                "audiInten": "-5590",
                "audiChange": "-28.7",
                "audiAcc": "1018557",
                "scrnCnt": "464",
                "showCnt": "683"
            },
            {
                "rnum": "5",
                "rank": "5",
                "rankInten": "-1",
                "rankOldAndNew": "OLD",
                "movieCd": "20247076",
                "movieNm": "귀멸의 칼날: 인연의 기적, 그리고 합동 강화 훈련으로",
                "openDt": "2024-02-14",
                "salesAmt": "82108100",
                "salesShare": "1.6",
                "salesInten": "-2969900",
                "salesChange": "-3.5",
                "salesAcc": "4830650300",
                "audiCnt": "9357",
                "audiInten": "1397",
                "audiChange": "17.6",
                "audiAcc": "419687",
                "scrnCnt": "274",
                "showCnt": "531"
            },
            {
                "rnum": "6",
                "rank": "6",
                "rankInten": "0",
                "rankOldAndNew": "OLD",
                "movieCd": "20231415",
                "movieNm": "소풍",
                "openDt": "2024-02-07",
                "salesAmt": "20473100",
                "salesShare": "0.4",
                "salesInten": "-19905355",
                "salesChange": "-49.3",
                "salesAcc": "2795985130",
                "audiCnt": "2574",
                "audiInten": "-2177",
                "audiChange": "-45.8",
                "audiAcc": "311951",
                "scrnCnt": "123",
                "showCnt": "143"
            },
            {
                "rnum": "7",
                "rank": "7",
                "rankInten": "8",
                "rankOldAndNew": "OLD",
                "movieCd": "20234730",
                "movieNm": "추락의 해부",
                "openDt": "2024-01-31",
                "salesAmt": "9846878",
                "salesShare": "0.2",
                "salesInten": "1634327",
                "salesChange": "19.9",
                "salesAcc": "805383834",
                "audiCnt": "1359",
                "audiInten": "489",
                "audiChange": "56.2",
                "audiAcc": "82023",
                "scrnCnt": "40",
                "showCnt": "45"
            },
            {
                "rnum": "8",
                "rank": "8",
                "rankInten": "9",
                "rankOldAndNew": "OLD",
                "movieCd": "20234641",
                "movieNm": "극장판 츠루네: 시작의 한 발",
                "openDt": "2024-02-21",
                "salesAmt": "11070748",
                "salesShare": "0.2",
                "salesInten": "5095346",
                "salesChange": "85.3",
                "salesAcc": "104314080",
                "audiCnt": "1349",
                "audiInten": "692",
                "audiChange": "105.3",
                "audiAcc": "11526",
                "scrnCnt": "63",
                "showCnt": "68"
            },
            {
                "rnum": "9",
                "rank": "9",
                "rankInten": "9",
                "rankOldAndNew": "OLD",
                "movieCd": "20247444",
                "movieNm": "월레스와 그로밋 더 클래식 컬렉션",
                "openDt": "2024-02-21",
                "salesAmt": "18042500",
                "salesShare": "0.3",
                "salesInten": "8318500",
                "salesChange": "85.5",
                "salesAcc": "169751000",
                "audiCnt": "1203",
                "audiInten": "554",
                "audiChange": "85.4",
                "audiAcc": "11340",
                "scrnCnt": "31",
                "showCnt": "35"
            },
            {
                "rnum": "10",
                "rank": "10",
                "rankInten": "-3",
                "rankOldAndNew": "OLD",
                "movieCd": "20247219",
                "movieNm": "사운드 오브 프리덤",
                "openDt": "2024-02-21",
                "salesAmt": "12479400",
                "salesShare": "0.2",
                "salesInten": "-17294200",
                "salesChange": "-58.1",
                "salesAcc": "407849300",
                "audiCnt": "1165",
                "audiInten": "-1687",
                "audiChange": "-59.2",
                "audiAcc": "37090",
                "scrnCnt": "116",
                "showCnt": "121"
            }
        ]
    }
}